streamlit_analytics2/__init__.py
streamlit_analytics2/config.py
streamlit_analytics2/display.py
streamlit_analytics2/firestore.py
streamlit_analytics2/main.py
streamlit_analytics2/state.py
streamlit_analytics2/utils.py
streamlit_analytics2/widgets.py
streamlit_analytics2/wrappers.py
streamlit_analytics2-0.10.4.dist-info/METADATA
streamlit_analytics2-0.10.4.dist-info/WHEEL
streamlit_analytics2-0.10.4.dist-info/licenses/LICENSE
streamlit_analytics2-0.10.4.dist-info/RECORD
