Metadata-Version: 2.4
Name: streamlit_analytics2
Version: 0.10.4
Summary: Track & visualize user interactions with your streamlit app.
Project-URL: Repository, https://github.com/444B/streamlit-analytics2
Project-URL: Documentation, https://github.com/444B/streamlit-analytics2/wiki
Project-URL: Issues, https://github.com/444B/streamlit-analytics2/issues
Author-email: 444B <contact+pypi@444b.me>
License: MIT License
License-File: LICENSE
Keywords: analytics,streamlit,streamlit-analytics,streamlit-analytics2,visualization
Classifier: Development Status :: 4 - Beta
Classifier: Intended Audience :: Developers
Classifier: License :: OSI Approved :: MIT License
Classifier: Operating System :: OS Independent
Classifier: Programming Language :: Python :: 3.9
Classifier: Programming Language :: Python :: 3.10
Classifier: Programming Language :: Python :: 3.11
Classifier: Programming Language :: Python :: 3.12
Classifier: Topic :: Database :: Front-Ends
Classifier: Topic :: Scientific/Engineering :: Information Analysis
Classifier: Topic :: Scientific/Engineering :: Visualization
Requires-Python: >=3.10
Requires-Dist: altair>=5.5.0
Requires-Dist: google-cloud-firestore>=2.19.0
Requires-Dist: numpy>=2.2.1
Requires-Dist: pandas>=2.2.3
Requires-Dist: streamlit>=1.37.0
Requires-Dist: typing-extensions>=4.12.2
Provides-Extra: dev
Requires-Dist: bandit>=1.8.0; extra == 'dev'
Requires-Dist: black>=24.10.0; extra == 'dev'
Requires-Dist: build>=1.2.2.post1; extra == 'dev'
Requires-Dist: flake8>=7.1.1; extra == 'dev'
Requires-Dist: isort>=5.13.2; extra == 'dev'
Requires-Dist: mypy>=1.14.0; extra == 'dev'
Requires-Dist: pandas-stubs>=2.2.3.241126; extra == 'dev'
Requires-Dist: pytest-cov>=4.0.0; extra == 'dev'
Requires-Dist: pytest>=8.3.4; extra == 'dev'
Requires-Dist: twine>=6.0.1; extra == 'dev'
Provides-Extra: test
Requires-Dist: pytest-cov>=4.0.0; extra == 'test'
Requires-Dist: pytest>=8.3.4; extra == 'test'
